LICENSE.txt
README.md
setup.py
act/__init__.py
act/act_ast.py
act/lex.py
act/parser.py
pts_act.egg-info/PKG-INFO
pts_act.egg-info/SOURCES.txt
pts_act.egg-info/dependency_links.txt
pts_act.egg-info/top_level.txt