Metadata-Version: 2.1
Name: pts-act
Version: 0.4.0
Summary: Parser for the ACT file format
Home-page: https://git.sr.ht/~martijnbraam/pts-act
Author: Martijn Braam
Author-email: martijn@brixit.nl
License: MIT
Platform: UNKNOWN
License-File: LICENSE.txt
